{"book-note_vuejs-design_1.md":"61895b4a","book-note_vuejs-design_2.md":"439b327b","book-note_vuejs-design_3.md":"410b009c","book-note_vuejs-design_4.md":"ec6c87e9","book-note_vuejs-design_5.md":"098f8b7e","book-note_vuejs-design_6.md":"9f35201e","book-note_vuejs-design_7.md":"fb3b4144","book-note_vuejs-design_8.md":"c390dc40","book-note_vuejs-design_z12.md":"dfc1af35","book-note_vuejs-design_z14.md":"5dbe8533","design_data-structure_linked_list.md":"fe5a3391","design_design-pattern_observer.md":"be68c1cf","design_design-pattern_publishers_subscribers.md":"f5c1a318","design_design-pattern_visitor.md":"6c3012ef","design_experience_comp.md":"c2e23e36","design_leetcode_lis.md":"9b0aaf77","design_leetcode_lru.md":"c3c1b26d","design_sort_bubblesort.md":"5a99fa8a","design_sort_heapsort.md":"7dd89db3","design_sort_index.md":"91c7bbb2","design_sort_insertionsort.md":"f704470b","design_sort_mergesort.md":"7c5dd58d","design_sort_selectionsort.md":"7400ab39","engineer_babel_babel.md":"6a1eb701","engineer_babel_plugin-transform-runtime.md":"679cb707","engineer_babel_preset-env.md":"1181c552","engineer_git_index.md":"6305d15c","engineer_linux_command.md":"bc7534fe","engineer_packages_esbuild.md":"a733d2eb","engineer_packages_ffmpeg.md":"49fa309e","engineer_packages_yalc.md":"f13f2813","engineer_rollup_index.md":"e9de2b39","engineer_stander_module.md":"6d1e6c8c","engineer_webpack_build_flow.md":"8eedd927","engineer_webpack_index.md":"acf2a321","index.md":"82bafaeb","interview_for_output_event-loop.md":"30eff50c","interview_for_output_proto.md":"ffe8077d","interview_handwriting_apply-call-bind.md":"7fd7af8d","interview_handwriting_array.md":"be34dfd9","interview_handwriting_big-add.md":"f7fe1d3c","interview_handwriting_currying.md":"d9771c07","interview_handwriting_debounce-throttle.md":"aefc88b8","interview_handwriting_deepclone.md":"3817026e","interview_index.md":"067069a8","interview_js_event-loop.md":"c36192ef","interview_other_index.md":"fdad1b57","interview_other_optimize.md":"322a3a57","interview_vue_index.md":"235f24a2","knowledge_browser_cache.md":"d84aeb3b","knowledge_browser_complier.md":"6e00bf48","knowledge_browser_cross-domain.md":"a2c4c465","knowledge_browser_event_loop.md":"aaf16220","knowledge_browser_framework.md":"6b9c6452","knowledge_browser_gc.md":"eb826a1f","knowledge_browser_jsbridge.md":"13a0f418","knowledge_browser_preload.md":"be70f271","knowledge_browser_render.md":"7483f264","knowledge_browser_repaint_reflow.md":"0cd55433","knowledge_browser_ssr.md":"11238137","knowledge_browser_vitals.md":"a98d5747","knowledge_css_bem.md":"44d3bd62","knowledge_css_bfc.md":"2ab8fd47","knowledge_css_box.md":"bcd01ac1","knowledge_css_display.md":"879e9693","knowledge_css_flex.md":"868cabb8","knowledge_css_px.md":"e5ee9040","knowledge_html_basic.md":"878f7bf4","knowledge_html_csp.md":"ffc5fac5","knowledge_html_seo.md":"6a77fd9d","knowledge_js_arrow_function.md":"3236529b","knowledge_js_call_apply_bind.md":"729020bf","knowledge_js_event.md":"0dd2483b","knowledge_js_generator.md":"faa7607d","knowledge_js_map_set.md":"9280d42c","knowledge_js_new.md":"3701b565","knowledge_js_promise.md":"adfebb82","knowledge_js_proto.md":"cd9d92c6","knowledge_js_proxy.md":"201f64c5","knowledge_js_symbol.md":"a6a441cd","knowledge_js_this.md":"c4b8a9d6","knowledge_js_typeof.md":"017d2c38","knowledge_js_var.md":"d2adebd2","knowledge_network_content-type.md":"e8354686","knowledge_network_cookie_session_token.md":"95ff6a50","knowledge_network_dns.md":"122dcdbc","knowledge_network_http-code.md":"b4cb3219","knowledge_network_http.md":"315ee598","knowledge_network_https.md":"0eb3d677","knowledge_network_security.md":"d6a0eea4","knowledge_network_tcp-udp.md":"54a3b970","knowledge_network_websocket.md":"7d9e9223","knowledge_ts_any-void.md":"f50bc4a7","knowledge_ts_index.md":"6ec6f6ff","knowledge_vue_basic.md":"fd4ca507","knowledge_vue_communication.md":"f26dfd85","knowledge_vue_diff.md":"db8d1289","knowledge_vue_directive.md":"08130d2f","knowledge_vue_keepalive.md":"a2c691a6","knowledge_vue_lifecycle.md":"377aba67","knowledge_vue_nexttick.md":"18d5fac9","knowledge_vue_pinia.md":"f9418fa3","knowledge_vue_slot.md":"1dccd1d0","knowledge_vue_templatecompiler.md":"a99b0a2f","knowledge_vue_v-model.md":"43b1cda2","knowledge_vue_vuex.md":"b1e7e541","knowledge_vue_watcher.md":"ce5840ee"}
