{"engineer_git_index.md":"2e8617d1","engineer_packages_yalc.md":"62a32a18","index.md":"4a3dc304","interview_for_output_event-loop.md":"ab532563","interview_for_output_proto.md":"4945d08f","interview_handwriting_apply-call-bind.md":"df9686b9","interview_handwriting_currying.md":"7d00e0e8","interview_handwriting_debounce-throttle.md":"378e29a1","interview_js_event-loop.md":"be5cb421","interview_other_index.md":"aa235662","knowledge_browser_cache.md":"514f5321","knowledge_browser_cross-domain.md":"6bfaab89","knowledge_browser_jsbridge.md":"4e122ee5","knowledge_browser_render.md":"05f692cd","knowledge_browser_repaint_reflow.md":"a14c5957","knowledge_browser_ssr.md":"b37575a7","knowledge_css_bfc.md":"6da1dbf6","knowledge_css_box.md":"11f48afa","knowledge_css_flex.md":"8f1c7e71","knowledge_html_basic.md":"c35b8dbc","knowledge_html_h5.md":"f77895ee","knowledge_html_seo.md":"2debae8c","knowledge_js_arrow_function.md":"77daffc2","knowledge_js_event.md":"e55620c4","knowledge_js_gc.md":"e47fdfc7","knowledge_js_new.md":"b31feccb","knowledge_js_proto.md":"6b149bd1","knowledge_js_this.md":"0ee683ca","knowledge_js_typeof.md":"e0b574ed","knowledge_network_content-type.md":"9863d5bd","knowledge_network_dns.md":"734de43b","knowledge_network_http-code.md":"03f493df","knowledge_network_http.md":"8097b2f1","knowledge_network_security.md":"0bdc6c5d","knowledge_network_tcp-udp.md":"c759dcd6","knowledge_network_websocket.md":"8c6f6eb4","knowledge_vue_directive.md":"1aaec61e"}
